pytest_publish.py
pytest_publish-1.2.0.dist-info/METADATA
pytest_publish-1.2.0.dist-info/WHEEL
pytest_publish-1.2.0.dist-info/entry_points.txt
pytest_publish-1.2.0.dist-info/RECORD
