Metadata-Version: 2.1
Name: pytest-publish
Version: 1.2.0
Summary: 
Author: Yuvalino
Author-email: yuvalino@gmail.com
Requires-Python: >=3.8,<4.0
Classifier: Programming Language :: Python :: 3
Classifier: Programming Language :: Python :: 3.8
Classifier: Programming Language :: Python :: 3.9
Classifier: Programming Language :: Python :: 3.10
Classifier: Programming Language :: Python :: 3.11
Classifier: Programming Language :: Python :: 3.12
Requires-Dist: dataclasses-json (>=0.6.6,<0.7.0)
Requires-Dist: filelock (>=3.14.0,<4.0.0)
Requires-Dist: pytest (>=8.0.0,<9.0.0)
Requires-Dist: requests (>=2.32.2,<3.0.0)
